{"slug":"nanyang_technological_university_biomedical_sciences_and_chinese_medicine","university":"Nanyang Technological University","school":"College of Science","degree":"Biomedical Sciences and Chinese Medicine","years_available":[2020,2021,2022,2023,2024],"latest_year":2024,"latest":{"year":2024,"employment_rate_overall":100.0,"employment_rate_ft_perm":85.7,"basic_monthly_mean":3298.0,"basic_monthly_median":3484.0,"gross_monthly_mean":3388.0,"gross_monthly_median":3485.0,"gross_mthly_25_percentile":3200.0,"gross_mthly_75_percentile":3500.0},"stats":{"salary_min":3000.0,"salary_max":3485.0,"salary_latest":3485.0,"salary_change_pct":16.2,"emp_latest":85.7},"metric_labels":{"employment_rate_overall":"Overall Employment Rate (%)","employment_rate_ft_perm":"Full-Time Permanent Employment Rate (%)","basic_monthly_mean":"Basic Monthly Mean ($)","basic_monthly_median":"Basic Monthly Median ($)","gross_monthly_mean":"Gross Monthly Mean ($)","gross_monthly_median":"Gross Monthly Median ($)","gross_mthly_25_percentile":"Gross Monthly 25th Percentile ($)","gross_mthly_75_percentile":"Gross Monthly 75th Percentile ($)"},"data":[{"year":2020,"employment_rate_overall":94.7,"employment_rate_ft_perm":84.2,"basic_monthly_mean":2950.0,"basic_monthly_median":3000.0,"gross_monthly_mean":2969.0,"gross_monthly_median":3000.0,"gross_mthly_25_percentile":2800.0,"gross_mthly_75_percentile":3150.0},{"year":2021,"employment_rate_overall":90.9,"employment_rate_ft_perm":77.3,"basic_monthly_mean":3023.0,"basic_monthly_median":3100.0,"gross_monthly_mean":3119.0,"gross_monthly_median":3100.0,"gross_mthly_25_percentile":2890.0,"gross_mthly_75_percentile":3300.0},{"year":2022,"employment_rate_overall":100.0,"employment_rate_ft_perm":90.0,"basic_monthly_mean":3300.0,"basic_monthly_median":3100.0,"gross_monthly_mean":3415.0,"gross_monthly_median":3175.0,"gross_mthly_25_percentile":3080.0,"gross_mthly_75_percentile":3300.0},{"year":2023,"employment_rate_overall":96.3,"employment_rate_ft_perm":85.2,"basic_monthly_mean":3297.0,"basic_monthly_median":3350.0,"gross_monthly_mean":3358.0,"gross_monthly_median":3350.0,"gross_mthly_25_percentile":3200.0,"gross_mthly_75_percentile":3600.0},{"year":2024,"employment_rate_overall":100.0,"employment_rate_ft_perm":85.7,"basic_monthly_mean":3298.0,"basic_monthly_median":3484.0,"gross_monthly_mean":3388.0,"gross_monthly_median":3485.0,"gross_mthly_25_percentile":3200.0,"gross_mthly_75_percentile":3500.0}]}